{
  "totalResultsCount": 47,
  "geonames": [
    {
      "adminCode1": "01",
      "lng": "136.90656",
      "geonameId": 1865694,
      "toponymName": "Aichi-ken",
      "countryId": "1861060",
      "fcl": "A",
      "population": 7408640,
      "countryCode": "JP",
      "name": "Aichi",
      "fclName": "country, state, region,...",
      "adminCodes1": {
        "ISO3166_2": "23"
      },
      "countryName": "Japan",
      "fcodeName": "first-order administrative division",
      "adminName1": "Aichi",
      "lat": "35.18017",
      "fcode": "ADM1"
    },
    {
      "adminCode1": "02",
      "lng": "140.4",
      "geonameId": 2113124,
      "toponymName": "Akita",
      "countryId": "1861060",
      "fcl": "A",
      "population": 1106050,
      "countryCode": "JP",
      "name": "Akita",
      "fclName": "country, state, region,...",
      "adminCodes1": {
        "ISO3166_2": "05"
      },
      "countryName": "Japan",
      "fcodeName": "first-order administrative division",
      "adminName1": "Akita",
      "lat": "39.75",
      "fcode": "ADM1"
    },
    {
      "adminCode1": "03",
      "lng": "140.82827",
      "geonameId": 2130656,
      "toponymName": "Aomori-ken",
      "countryId": "1861060",
      "fcl": "A",
      "population": 1373164,
      "countryCode": "JP",
      "name": "Aomori",
      "fclName": "country, state, region,...",
      "adminCodes1": {
        "ISO3166_2": "02"
      },
      "countryName": "Japan",
      "fcodeName": "first-order administrative division",
      "adminName1": "Aomori",
      "lat": "40.7831",
      "fcode": "ADM1"
    },
    {
      "adminCode1": "04",
      "lng": "140.12333",
      "geonameId": 2113014,
      "toponymName": "Chiba-ken",
      "countryId": "1861060",
      "fcl": "A",
      "population": 6201046,
      "countryCode": "JP",
      "name": "Chiba",
      "fclName": "country, state, region,...",
      "adminCodes1": {
        "ISO3166_2": "12"
      },
      "countryName": "Japan",
      "fcodeName": "first-order administrative division",
      "adminName1": "Chiba",
      "lat": "35.60506",
      "fcode": "ADM1"
    },
    {
      "adminCode1": "05",
      "lng": "132.85",
      "geonameId": 1864226,
      "toponymName": "Ehime",
      "countryId": "1861060",
      "fcl": "A",
      "population": 1476750,
      "countryCode": "JP",
      "name": "Ehime",
      "fclName": "country, state, region,...",
      "adminCodes1": {
        "ISO3166_2": "38"
      },
      "countryName": "Japan",
      "fcodeName": "first-order administrative division",
      "adminName1": "Ehime",
      "lat": "33.61667",
      "fcode": "ADM1"
    },
    {
      "adminCode1": "06",
      "lng": "136.21667",
      "geonameId": 1863983,
      "toponymName": "Fukui",
      "countryId": "1861060",
      "fcl": "A",
      "population": 795437,
      "countryCode": "JP",
      "name": "Fukui",
      "fclName": "country, state, region,...",
      "adminCodes1": {
        "ISO3166_2": "18"
      },
      "countryName": "Japan",
      "fcodeName": "first-order administrative division",
      "adminName1": "Fukui",
      "lat": "35.85",
      "fcode": "ADM1"
    },
    {
      "adminCode1": "07",
      "lng": "130.66472",
      "geonameId": 1863958,
      "toponymName": "Fukuoka Prefecture",
      "countryId": "1861060",
      "fcl": "A",
      "population": 5088483,
      "countryCode": "JP",
      "name": "Fukuoka",
      "fclName": "country, state, region,...",
      "adminCodes1": {
        "ISO3166_2": "40"
      },
      "countryName": "Japan",
      "fcodeName": "first-order administrative division",
      "adminName1": "Fukuoka",
      "lat": "33.52813",
      "fcode": "ADM1"
    },
    {
      "adminCode1": "08",
      "lng": "140.22199",
      "geonameId": 2112922,
      "toponymName": "Fukushima-ken",
      "countryId": "1861060",
      "fcl": "A",
      "population": 2028752,
      "countryCode": "JP",
      "name": "Fukushima",
      "fclName": "country, state, region,...",
      "adminCodes1": {
        "ISO3166_2": "07"
      },
      "countryName": "Japan",
      "fcodeName": "first-order administrative division",
      "adminName1": "Fukushima",
      "lat": "37.38158",
      "fcode": "ADM1"
    },
    {
      "adminCode1": "09",
      "lng": "137.05",
      "geonameId": 1863640,
      "toponymName": "Gifu",
      "countryId": "1861060",
      "fcl": "A",
      "population": 2074158,
      "countryCode": "JP",
      "name": "Gifu",
      "fclName": "country, state, region,...",
      "adminCodes1": {
        "ISO3166_2": "21"
      },
      "countryName": "Japan",
      "fcodeName": "first-order administrative division",
      "adminName1": "Gifu",
      "lat": "35.78333",
      "fcode": "ADM1"
    },
    {
      "adminCode1": "10",
      "lng": "138.98235",
      "geonameId": 1863501,
      "toponymName": "Gunma-ken",
      "countryId": "1861060",
      "fcl": "A",
      "population": 2014608,
      "countryCode": "JP",
      "name": "Gunma",
      "fclName": "country, state, region,...",
      "adminCodes1": {
        "ISO3166_2": "10"
      },
      "countryName": "Japan",
      "fcodeName": "first-order administrative division",
      "adminName1": "Gunma",
      "lat": "36.50747",
      "fcode": "ADM1"
    },
    {
      "adminCode1": "11",
      "lng": "132.78543",
      "geonameId": 1862413,
      "toponymName": "Hiroshima-ken",
      "countryId": "1861060",
      "fcl": "A",
      "population": 2857990,
      "countryCode": "JP",
      "name": "Hiroshima",
      "fclName": "country, state, region,...",
      "adminCodes1": {
        "ISO3166_2": "34"
      },
      "countryName": "Japan",
      "fcodeName": "first-order administrative division",
      "adminName1": "Hiroshima",
      "lat": "34.60673",
      "fcode": "ADM1"
    },
    {
      "adminCode1": "12",
      "lng": "141.3466",
      "geonameId": 2130037,
      "toponymName": "Hokkaido",
      "countryId": "1861060",
      "fcl": "A",
      "population": 5647230,
      "countryCode": "JP",
      "name": "Hokkaido",
      "fclName": "country, state, region,...",
      "adminCodes1": {
        "ISO3166_2": "01"
      },
      "countryName": "Japan",
      "fcodeName": "first-order administrative division",
      "adminName1": "Hokkaido",
      "lat": "43.06451",
      "fcode": "ADM1"
    },
    {
      "adminCode1": "13",
      "lng": "134.81667",
      "geonameId": 1862047,
      "toponymName": "Hyōgo",
      "countryId": "1861060",
      "fcl": "A",
      "population": 5582978,
      "countryCode": "JP",
      "name": "Hyōgo",
      "fclName": "country, state, region,...",
      "adminCodes1": {
        "ISO3166_2": "28"
      },
      "countryName": "Japan",
      "fcodeName": "first-order administrative division",
      "adminName1": "Hyōgo",
      "lat": "35.03333",
      "fcode": "ADM1"
    },
    {
      "adminCode1": "14",
      "lng": "140.31667",
      "geonameId": 2112669,
      "toponymName": "Ibaraki",
      "countryId": "1861060",
      "fcl": "A",
      "population": 2964141,
      "countryCode": "JP",
      "name": "Ibaraki",
      "fclName": "country, state, region,...",
      "adminCodes1": {
        "ISO3166_2": "08"
      },
      "countryName": "Japan",
      "fcodeName": "first-order administrative division",
      "adminName1": "Ibaraki",
      "lat": "36.3",
      "fcode": "ADM1"
    },
    {
      "adminCode1": "15",
      "lng": "136.7705",
      "geonameId": 1861387,
      "toponymName": "Ishikawa-ken",
      "countryId": "1861060",
      "fcl": "A",
      "population": 1168929,
      "countryCode": "JP",
      "name": "Ishikawa",
      "fclName": "country, state, region,...",
      "adminCodes1": {
        "ISO3166_2": "17"
      },
      "countryName": "Japan",
      "fcodeName": "first-order administrative division",
      "adminName1": "Ishikawa",
      "lat": "36.77145",
      "fcode": "ADM1"
    },
    {
      "adminCode1": "16",
      "lng": "141.35",
      "geonameId": 2112518,
      "toponymName": "Iwate",
      "countryId": "1861060",
      "fcl": "A",
      "population": 1330530,
      "countryCode": "JP",
      "name": "Iwate",
      "fclName": "country, state, region,...",
      "adminCodes1": {
        "ISO3166_2": "03"
      },
      "countryName": "Japan",
      "fcodeName": "first-order administrative division",
      "adminName1": "Iwate",
      "lat": "39.6",
      "fcode": "ADM1"
    },
    {
      "adminCode1": "17",
      "lng": "133.99471",
      "geonameId": 1860834,
      "toponymName": "Kagawa-ken",
      "countryId": "1861060",
      "fcl": "A",
      "population": 995465,
      "countryCode": "JP",
      "name": "Kagawa",
      "fclName": "country, state, region,...",
      "adminCodes1": {
        "ISO3166_2": "37"
      },
      "countryName": "Japan",
      "fcodeName": "first-order administrative division",
      "adminName1": "Kagawa",
      "lat": "34.24717",
      "fcode": "ADM1"
    },
    {
      "adminCode1": "18",
      "lng": "130.99301",
      "geonameId": 1860825,
      "toponymName": "Kagoshima-ken",
      "countryId": "1861060",
      "fcl": "A",
      "population": 1703406,
      "countryCode": "JP",
      "name": "Kagoshima",
      "fclName": "country, state, region,...",
      "adminCodes1": {
        "ISO3166_2": "46"
      },
      "countryName": "Japan",
      "fcodeName": "first-order administrative division",
      "adminName1": "Kagoshima",
      "lat": "31.59303",
      "fcode": "ADM1"
    },
    {
      "adminCode1": "19",
      "lng": "139.33333",
      "geonameId": 1860291,
      "toponymName": "Kanagawa",
      "countryId": "1861060",
      "fcl": "A",
      "population": 9097401,
      "countryCode": "JP",
      "name": "Kanagawa",
      "fclName": "country, state, region,...",
      "adminCodes1": {
        "ISO3166_2": "14"
      },
      "countryName": "Japan",
      "fcodeName": "first-order administrative division",
      "adminName1": "Kanagawa",
      "lat": "35.41667",
      "fcode": "ADM1"
    },
    {
      "adminCode1": "20",
      "lng": "133.36667",
      "geonameId": 1859133,
      "toponymName": "Kochi Prefecture",
      "countryId": "1861060",
      "fcl": "A",
      "population": 757914,
      "countryCode": "JP",
      "name": "Kochi",
      "fclName": "country, state, region,...",
      "adminCodes1": {
        "ISO3166_2": "39"
      },
      "countryName": "Japan",
      "fcodeName": "first-order administrative division",
      "adminName1": "Kochi",
      "lat": "33.58333",
      "fcode": "ADM1"
    },
    {
      "adminCode1": "21",
      "lng": "130.75",
      "geonameId": 1858419,
      "toponymName": "Kumamoto",
      "countryId": "1861060",
      "fcl": "A",
      "population": 1812255,
      "countryCode": "JP",
      "name": "Kumamoto",
      "fclName": "country, state, region,...",
      "adminCodes1": {
        "ISO3166_2": "43"
      },
      "countryName": "Japan",
      "fcodeName": "first-order administrative division",
      "adminName1": "Kumamoto",
      "lat": "32.61667",
      "fcode": "ADM1"
    },
    {
      "adminCode1": "22",
      "lng": "135.43333",
      "geonameId": 1857907,
      "toponymName": "Kyoto Prefecture",
      "countryId": "1861060",
      "fcl": "A",
      "population": 2633428,
      "countryCode": "JP",
      "name": "Kyoto",
      "fclName": "country, state, region,...",
      "adminCodes1": {
        "ISO3166_2": "26"
      },
      "countryName": "Japan",
      "fcodeName": "first-order administrative division",
      "adminName1": "Kyoto",
      "lat": "35.25",
      "fcode": "ADM1"
    },
    {
      "adminCode1": "23",
      "lng": "136.38296",
      "geonameId": 1857352,
      "toponymName": "Mie-ken",
      "countryId": "1861060",
      "fcl": "A",
      "population": 1855000,
      "countryCode": "JP",
      "name": "Mie",
      "fclName": "country, state, region,...",
      "adminCodes1": {
        "ISO3166_2": "24"
      },
      "countryName": "Japan",
      "fcodeName": "first-order administrative division",
      "adminName1": "Mie",
      "lat": "34.52123",
      "fcode": "ADM1"
    },
    {
      "adminCode1": "24",
      "lng": "140.92624",
      "geonameId": 2111888,
      "toponymName": "Miyagi-ken",
      "countryId": "1861060",
      "fcl": "A",
      "population": 2337514,
      "countryCode": "JP",
      "name": "Miyagi",
      "fclName": "country, state, region,...",
      "adminCodes1": {
        "ISO3166_2": "04"
      },
      "countryName": "Japan",
      "fcodeName": "first-order administrative division",
      "adminName1": "Miyagi",
      "lat": "38.44938",
      "fcode": "ADM1"
    },
    {
      "adminCode1": "25",
      "lng": "131.3",
      "geonameId": 1856710,
      "toponymName": "Miyazaki",
      "countryId": "1861060",
      "fcl": "A",
      "population": 1128412,
      "countryCode": "JP",
      "name": "Miyazaki",
      "fclName": "country, state, region,...",
      "adminCodes1": {
        "ISO3166_2": "45"
      },
      "countryName": "Japan",
      "fcodeName": "first-order administrative division",
      "adminName1": "Miyazaki",
      "lat": "32.2",
      "fcode": "ADM1"
    },
    {
      "adminCode1": "26",
      "lng": "138.04077",
      "geonameId": 1856210,
      "toponymName": "Nagano-ken",
      "countryId": "1861060",
      "fcl": "A",
      "population": 2148425,
      "countryCode": "JP",
      "name": "Nagano",
      "fclName": "country, state, region,...",
      "adminCodes1": {
        "ISO3166_2": "20"
      },
      "countryName": "Japan",
      "fcodeName": "first-order administrative division",
      "adminName1": "Nagano",
      "lat": "36.13464",
      "fcode": "ADM1"
    },
    {
      "adminCode1": "27",
      "lng": "129.6",
      "geonameId": 1856156,
      "toponymName": "Nagasaki Prefecture",
      "countryId": "1861060",
      "fcl": "A",
      "population": 1407904,
      "countryCode": "JP",
      "name": "Nagasaki",
      "fclName": "country, state, region,...",
      "adminCodes1": {
        "ISO3166_2": "42"
      },
      "countryName": "Japan",
      "fcodeName": "first-order administrative division",
      "adminName1": "Nagasaki",
      "lat": "33.23333",
      "fcode": "ADM1"
    },
    {
      "adminCode1": "28",
      "lng": "135.83289",
      "geonameId": 1855608,
      "toponymName": "Nara-ken",
      "countryId": "1861060",
      "fcl": "A",
      "population": 1396849,
      "countryCode": "JP",
      "name": "Nara",
      "fclName": "country, state, region,...",
      "adminCodes1": {
        "ISO3166_2": "29"
      },
      "countryName": "Japan",
      "fcodeName": "first-order administrative division",
      "adminName1": "Nara",
      "lat": "34.68525",
      "fcode": "ADM1"
    },
    {
      "adminCode1": "29",
      "lng": "138.91748",
      "geonameId": 1855429,
      "toponymName": "Niigata-ken",
      "countryId": "1861060",
      "fcl": "A",
      "population": 2371000,
      "countryCode": "JP",
      "name": "Niigata",
      "fclName": "country, state, region,...",
      "adminCodes1": {
        "ISO3166_2": "15"
      },
      "countryName": "Japan",
      "fcodeName": "first-order administrative division",
      "adminName1": "Niigata",
      "lat": "37.52343",
      "fcode": "ADM1"
    },
    {
      "adminCode1": "30",
      "lng": "131.43353",
      "geonameId": 1854484,
      "toponymName": "Oita Prefecture",
      "countryId": "1861060",
      "fcl": "A",
      "population": 1159600,
      "countryCode": "JP",
      "name": "Oita",
      "fclName": "country, state, region,...",
      "adminCodes1": {
        "ISO3166_2": "44"
      },
      "countryName": "Japan",
      "fcodeName": "first-order administrative division",
      "adminName1": "Oita",
      "lat": "33.19899",
      "fcode": "ADM1"
    },
    {
      "adminCode1": "31",
      "lng": "133.81018",
      "geonameId": 1854381,
      "toponymName": "Okayama-ken",
      "countryId": "1861060",
      "fcl": "A",
      "population": 1940000,
      "countryCode": "JP",
      "name": "Okayama",
      "fclName": "country, state, region,...",
      "adminCodes1": {
        "ISO3166_2": "33"
      },
      "countryName": "Japan",
      "fcodeName": "first-order administrative division",
      "adminName1": "Okayama",
      "lat": "34.90204",
      "fcode": "ADM1"
    },
    {
      "adminCode1": "47",
      "lng": "127.93333",
      "geonameId": 1854345,
      "toponymName": "Okinawa",
      "countryId": "1861060",
      "fcl": "A",
      "population": 1416587,
      "countryCode": "JP",
      "name": "Okinawa",
      "fclName": "country, state, region,...",
      "adminCodes1": {
        "ISO3166_2": "47"
      },
      "countryName": "Japan",
      "fcodeName": "first-order administrative division",
      "adminName1": "Okinawa",
      "lat": "26.5",
      "fcode": "ADM1"
    },
    {
      "adminCode1": "33",
      "lng": "130.11491",
      "geonameId": 1853299,
      "toponymName": "Saga-ken",
      "countryId": "1861060",
      "fcl": "A",
      "population": 839458,
      "countryCode": "JP",
      "name": "Saga",
      "fclName": "country, state, region,...",
      "adminCodes1": {
        "ISO3166_2": "41"
      },
      "countryName": "Japan",
      "fcodeName": "first-order administrative division",
      "adminName1": "Saga",
      "lat": "33.28904",
      "fcode": "ADM1"
    },
    {
      "adminCode1": "34",
      "lng": "139.64904",
      "geonameId": 1853226,
      "toponymName": "Saitama-ken",
      "countryId": "1861060",
      "fcl": "A",
      "population": 7190817,
      "countryCode": "JP",
      "name": "Saitama",
      "fclName": "country, state, region,...",
      "adminCodes1": {
        "ISO3166_2": "11"
      },
      "countryName": "Japan",
      "fcodeName": "first-order administrative division",
      "adminName1": "Saitama",
      "lat": "35.85721",
      "fcode": "ADM1"
    },
    {
      "adminCode1": "35",
      "lng": "136.13333",
      "geonameId": 1852553,
      "toponymName": "Shiga",
      "countryId": "1861060",
      "fcl": "A",
      "population": 1402132,
      "countryCode": "JP",
      "name": "Shiga",
      "fclName": "country, state, region,...",
      "adminCodes1": {
        "ISO3166_2": "25"
      },
      "countryName": "Japan",
      "fcodeName": "first-order administrative division",
      "adminName1": "Shiga",
      "lat": "35.21667",
      "fcode": "ADM1"
    },
    {
      "adminCode1": "36",
      "lng": "132.56111",
      "geonameId": 1852442,
      "toponymName": "Shimane-ken",
      "countryId": "1861060",
      "fcl": "A",
      "population": 712336,
      "countryCode": "JP",
      "name": "Shimane",
      "fclName": "country, state, region,...",
      "adminCodes1": {
        "ISO3166_2": "32"
      },
      "countryName": "Japan",
      "fcodeName": "first-order administrative division",
      "adminName1": "Shimane",
      "lat": "35.07693",
      "fcode": "ADM1"
    },
    {
      "adminCode1": "37",
      "lng": "138.33333",
      "geonameId": 1851715,
      "toponymName": "Shizuoka",
      "countryId": "1861060",
      "fcl": "A",
      "population": 3774471,
      "countryCode": "JP",
      "name": "Shizuoka",
      "fclName": "country, state, region,...",
      "adminCodes1": {
        "ISO3166_2": "22"
      },
      "countryName": "Japan",
      "fcodeName": "first-order administrative division",
      "adminName1": "Shizuoka",
      "lat": "35.01667",
      "fcode": "ADM1"
    },
    {
      "adminCode1": "38",
      "lng": "139.81667",
      "geonameId": 1850310,
      "toponymName": "Tochigi",
      "countryId": "1861060",
      "fcl": "A",
      "population": 2017548,
      "countryCode": "JP",
      "name": "Tochigi",
      "fclName": "country, state, region,...",
      "adminCodes1": {
        "ISO3166_2": "09"
      },
      "countryName": "Japan",
      "fcodeName": "first-order administrative division",
      "adminName1": "Tochigi",
      "lat": "36.7",
      "fcode": "ADM1"
    },
    {
      "adminCode1": "39",
      "lng": "134.23682",
      "geonameId": 1850157,
      "toponymName": "Tokushima-ken",
      "countryId": "1861060",
      "fcl": "A",
      "population": 824108,
      "countryCode": "JP",
      "name": "Tokushima",
      "fclName": "country, state, region,...",
      "adminCodes1": {
        "ISO3166_2": "36"
      },
      "countryName": "Japan",
      "fcodeName": "first-order administrative division",
      "adminName1": "Tokushima",
      "lat": "33.92176",
      "fcode": "ADM1"
    },
    {
      "adminCode1": "40",
      "lng": "139.69171",
      "geonameId": 1850144,
      "toponymName": "Tokyo Prefecture",
      "countryId": "1861060",
      "fcl": "A",
      "population": 12445327,
      "countryCode": "JP",
      "name": "Tokyo",
      "fclName": "country, state, region,...",
      "adminCodes1": {
        "ISO3166_2": "13"
      },
      "countryName": "Japan",
      "fcodeName": "first-order administrative division",
      "adminName1": "Tokyo",
      "lat": "35.6895",
      "fcode": "ADM1"
    },
    {
      "adminCode1": "41",
      "lng": "133.85",
      "geonameId": 1849890,
      "toponymName": "Tottori",
      "countryId": "1861060",
      "fcl": "A",
      "population": 584982,
      "countryCode": "JP",
      "name": "Tottori",
      "fclName": "country, state, region,...",
      "adminCodes1": {
        "ISO3166_2": "31"
      },
      "countryName": "Japan",
      "fcodeName": "first-order administrative division",
      "adminName1": "Tottori",
      "lat": "35.4",
      "fcode": "ADM1"
    },
    {
      "adminCode1": "42",
      "lng": "137.26513",
      "geonameId": 1849872,
      "toponymName": "Toyama-ken",
      "countryId": "1861060",
      "fcl": "A",
      "population": 1104239,
      "countryCode": "JP",
      "name": "Toyama",
      "fclName": "country, state, region,...",
      "adminCodes1": {
        "ISO3166_2": "16"
      },
      "countryName": "Japan",
      "fcodeName": "first-order administrative division",
      "adminName1": "Toyama",
      "lat": "36.63926",
      "fcode": "ADM1"
    },
    {
      "adminCode1": "43",
      "lng": "135.41667",
      "geonameId": 1848938,
      "toponymName": "Wakayama",
      "countryId": "1861060",
      "fcl": "A",
      "population": 989983,
      "countryCode": "JP",
      "name": "Wakayama",
      "fclName": "country, state, region,...",
      "adminCodes1": {
        "ISO3166_2": "30"
      },
      "countryName": "Japan",
      "fcodeName": "first-order administrative division",
      "adminName1": "Wakayama",
      "lat": "33.91667",
      "fcode": "ADM1"
    },
    {
      "adminCode1": "44",
      "lng": "140.0997",
      "geonameId": 2110554,
      "toponymName": "Yamagata-ken",
      "countryId": "1861060",
      "fcl": "A",
      "population": 1152000,
      "countryCode": "JP",
      "name": "Yamagata",
      "fclName": "country, state, region,...",
      "adminCodes1": {
        "ISO3166_2": "06"
      },
      "countryName": "Japan",
      "fcodeName": "first-order administrative division",
      "adminName1": "Yamagata",
      "lat": "38.4503",
      "fcode": "ADM1"
    },
    {
      "adminCode1": "45",
      "lng": "131.56667",
      "geonameId": 1848681,
      "toponymName": "Yamaguchi",
      "countryId": "1861060",
      "fcl": "A",
      "population": 1445702,
      "countryCode": "JP",
      "name": "Yamaguchi",
      "fclName": "country, state, region,...",
      "adminCodes1": {
        "ISO3166_2": "35"
      },
      "countryName": "Japan",
      "fcodeName": "first-order administrative division",
      "adminName1": "Yamaguchi",
      "lat": "34.2",
      "fcode": "ADM1"
    },
    {
      "adminCode1": "46",
      "lng": "138.6",
      "geonameId": 1848649,
      "toponymName": "Yamanashi",
      "countryId": "1861060",
      "fcl": "A",
      "population": 845022,
      "countryCode": "JP",
      "name": "Yamanashi",
      "fclName": "country, state, region,...",
      "adminCodes1": {
        "ISO3166_2": "19"
      },
      "countryName": "Japan",
      "fcodeName": "first-order administrative division",
      "adminName1": "Yamanashi",
      "lat": "35.61667",
      "fcode": "ADM1"
    },
    {
      "adminCode1": "32",
      "lng": "135.51968",
      "geonameId": 1853904,
      "toponymName": "Ōsaka-fu",
      "countryId": "1861060",
      "fcl": "A",
      "population": 8864228,
      "countryCode": "JP",
      "name": "Ōsaka",
      "fclName": "country, state, region,...",
      "adminCodes1": {
        "ISO3166_2": "27"
      },
      "countryName": "Japan",
      "fcodeName": "first-order administrative division",
      "adminName1": "Ōsaka",
      "lat": "34.68631",
      "fcode": "ADM1"
    }
  ]
}